code/__init__.py
AlaaJassimMohammed-0.1.dist-info/LICENSE.txt
AlaaJassimMohammed-0.1.dist-info/METADATA
AlaaJassimMohammed-0.1.dist-info/WHEEL
AlaaJassimMohammed-0.1.dist-info/top_level.txt
AlaaJassimMohammed-0.1.dist-info/RECORD
