Metadata-Version: 2.1
Name: AlaaJassimMohammed
Version: 0.1
Summary: Small and simple image processing library
Author: Alaa Jassim Mohammed
Classifier: Programming Language :: Python :: 3
Classifier: Operating System :: OS Independent
Classifier: License :: OSI Approved :: MIT License
License-File: LICENSE.txt
